mandrill_logger/__init__.py
mandrill_logger/admin.py
mandrill_logger/enums.py
mandrill_logger/models.py
mandrill_logger/tests.py
mandrill_logger/utils.py
mandrill_logger/views.py
mandrill_logger/migrations/0001_initial.py
mandrill_logger/migrations/0002_auto_20160331_1401.py
mandrill_logger/migrations/__init__.py
mandrill_logger-0.0.7.dist-info/METADATA
mandrill_logger-0.0.7.dist-info/RECORD
mandrill_logger-0.0.7.dist-info/WHEEL
mandrill_logger-0.0.7.dist-info/top_level.txt
