Metadata-Version: 2.1
Name: mandrill-logger
Version: 0.0.7
Summary: Django logging for Mandrill
Home-page: https://github.com/willandskill/mandrill_logger
Author: Will & Skill
Author-email: info@willandskill.se
License: MIT licence, see LICENCE.txt
Platform: UNKNOWN
